Workbook
Name A: '06_Calculations'!$A$1

Sheet 00_ReadMe
A1: Renewable Energy Portfolio FP&A & Business Control Model
A3: Workbook purpose
A4: This workbook is a synthetic FP&A and business control model for a renewable energy asset portfolio. It compares actuals, budget, and forecast performance across revenue, EBITDA, production, downtime, and variance drivers.
A8: How to use this workbook
A9: 1. Start with the Management Dashboard for the executive view.
A10: 2. Review the Calculations sheet for portfolio and asset-level summaries.
A11: 3. Use the Variance Analysis sheet to understand the EBITDA bridge from budget to actual.
A12: 4. Use the Scenario Model to test Downside, Base, and Upside assumptions.
A13: 5. Read the Commentary Pack for the management interpretation.
A15: Workbook structure
A16: 00_ReadMe: Workbook guide and usage notes
A17: 01_Assumptions: Business assumptions and scenario logic
... A34: Version 1.0 - Last updated: 23 May 2026

Sheet 01_Assumptions
A1: Model Assumptions
A3: Portfolio scope
A4: The model represents a synthetic renewable energy portfolio with offshore wind, solar PV, battery storage, and hydrogen pilot assets.
A5: The reporting period covers monthly performance from Jan-25 to Dec-26.
A6: The model compares actuals, budget, and forecast performance across revenue, EBITDA, capex, production, downtime, and availability.
A8: Scenario logic
A9: Downside: lower price realization, weaker production, higher opex inflation, higher downtime, and delayed capex/ramp-up.
A10: Base: moderate price and volume assumptions with continued margin pressure.
A11: Upside: stronger price realization, better utilization, lower downtime, and improved operating leverage.
A14: Key modeling assumptions
A15: Revenue is modeled as production volume multiplied by realized price, with battery and hydrogen treated as MWh-equivalent output.
A16: EBITDA equals revenue minus direct opex and allocated overhead.
... A25: In a real FP&A setting, assumptions would require source validation, stakeholder review, sensitivity testing, and reconciliation to accounting systems.

Sheet 02_Raw_Data_Checks
A1: Raw Data Checks
A3: Check | B3: Result | C3: Expected | D3: Status
A4: Assets row count | B4: =ROWS(assets[]) -> 5 | C4: 5 | D4: =IF(B4=C4,"Pass","Check") -> Pass
A5: Actuals row count | B5: =ROWS(monthly_actuals[]) -> 120 | C5: 120 | D5: =IF(B5=C5,"Pass","Check") -> Pass
A6: Budget row count | B6: =ROWS(monthly_budget[]) -> 120 | C6: 120 | D6: =IF(B6=C6,"Pass","Check") -> Pass
A7: Forecast row count | B7: =ROWS(monthly_forecast[]) -> 120 | C7: 120 | D7: =IF(B7=C7,"Pass","Check") -> Pass
A8: Variance driver row count | B8: =ROWS(variance_drivers[]) -> 720 | C8: 720 | D8: =IF(B8=C8,"Pass","Check") -> Pass
A9: Combined table row count | B9: =ROWS(fpna_monthly_combined[]) -> 360 | C9: 360 | D9: =IF(B9=C9,"Pass","Check") -> Pass

Sheet 03_PQ_Actuals
A1: month | B1: asset_id | C1: production_mwh | D1: realized_price_eur_mwh | E1: revenue_eur | F1: direct_opex_eur | G1: allocated_overhead_eur | H1: ebitda_eur | I1: capex_eur | J1: utilization_pct | K1: downtime_hours | L1: availability_pct | M1: Scenario
A2: 45658 | B2: A001 | C2: 62933 | D2: 82.4 | E2: 5185781 | F2: 1247706 | G2: 156000 | H2: 3782075 | I2: 61200 | J2: 0.4699 | K2: 6 | L2: 0.9919 | M2: Actual
A3: 45658 | B3: A002 | C3: 3160.7 | D3: 86.15 | E3: 272299 | F3: 106430 | G3: 43050 | H3: 122818 | I3: 8035 | J3: 0.0566 | K3: 2 | L3: 0.9973 | M3: Actual
A4: 45658 | B4: A003 | C4: 1670.1 | D4: 82.79 | E4: 138261 | F4: 64426 | G4: 30750 | H4: 43085 | I4: 8258 | J4: 0.0534 | K4: 2 | L4: 0.9973 | M4: Actual
A5: 45658 | B5: A004 | C5: 10528.6 | D5: 41.77 | E5: 439751 | F5: 311898 | G5: 67600 | H5: 60252 | I5: 185500 | J5: 0.2359 | K5: 18 | L5: 0.9758 | M5: Actual
A6: 45658 | B6: A005 | C6: 1501 | D6: 117.48 | E6: 176343 | F6: 754744 | G6: 100700 | H6: -679101 | I6: 676000 | J6: 0.1009 | K6: 24 | L6: 0.9677 | M6: Actual
A7: 45689 | B7: A001 | C7: 57178.3 | D7: 79.18 | E7: 4527633 | F7: 1158840 | G7: 156000 | H7: 3212794 | I7: 61200 | J7: 0.4727 | K7: 6 | L7: 0.9911 | M7: Actual
A8: 45689 | B8: A002 | C8: 3885.3 | D8: 79.61 | E8: 309293 | F8: 110349 | G8: 43050 | H8: 155894 | I8: 7910 | J8: 0.0771 | K8: 8 | L8: 0.9881 | M8: Actual
A9: 45689 | B9: A003 | C9: 2333 | D9: 81.31 | E9: 189690 | F9: 66027 | G9: 30750 | H9: 92913 | I9: 8917 | J9: 0.0827 | K9: 8 | L9: 0.9881 | M9: Actual
A10: 45689 | B10: A004 | C10: 10519.2 | D10: 41.5 | E10: 436589 | F10: 358729 | G10: 67600 | H10: 10261 | I10: 185500 | J10: 0.2609 | K10: 14 | L10: 0.9792 | M10: Actual
A11: 45689 | B11: A005 | C11: 1553.9 | D11: 117.96 | E11: 183303 | F11: 753742 | G11: 100700 | H11: -671138 | I11: 676000 | J11: 0.1156 | K11: 24 | L11: 0.9643 | M11: Actual
A12: 45717 | B12: A001 | C12: 59753.4 | D12: 77.15 | E12: 4610246 | F12: 1215684 | G12: 156000 | H12: 3238562 | I12: 61200 | J12: 0.4462 | K12: 6 | L12: 0.9919 | M12: Actual
A13: 45717 | B13: A002 | C13: 6698.1 | D13: 74.04 | E13: 495931 | F13: 120794 | G13: 43050 | H13: 332087 | I13: 28576 | J13: 0.12 | K13: 2 | L13: 0.9973 | M13: Actual
... A121: 46357 | B121: A005 | C121: 6973.9 | D121: 118.08 | E121: 823503 | F121: 1168373 | G121: 100700 | H121: -445570 | I121: 436800 | J121: 0.4687 | K121: 30 | L121: 0.9597 | M121: Actual

Sheet 04_PQ_Budget
A1: month | B1: asset_id | C1: production_mwh | D1: realized_price_eur_mwh | E1: revenue_eur | F1: direct_opex_eur | G1: allocated_overhead_eur | H1: ebitda_eur | I1: capex_eur | J1: utilization_pct | K1: downtime_hours | L1: availability_pct | M1: Scenario
A2: 45658 | B2: A001 | C2: 66420 | D2: 92 | E2: 6110640 | F2: 1181360 | G2: 150000 | H2: 4779280 | I2: 60000 | J2: 0.496 | K2: 6 | L2: 0.9919 | M2: Budget
A3: 45658 | B3: A002 | C3: 3060.8 | D3: 85 | E3: 260164 | F3: 104794 | G3: 42000 | H3: 113369 | I3: 8000 | J3: 0.0549 | K3: 2 | L3: 0.9973 | M3: Budget
A4: 45658 | B4: A003 | C4: 1714 | D4: 85 | E4: 145692 | F4: 62485 | G4: 30000 | H4: 53207 | I4: 8000 | J4: 0.0549 | K4: 2 | L4: 0.9973 | M4: Budget
A5: 45658 | B5: A004 | C5: 12220 | D5: 41.55 | E5: 507741 | F5: 283544 | G5: 65000 | H5: 159197 | I5: 175000 | J5: 0.2737 | K5: 6 | L5: 0.9919 | M5: Budget
A6: 45658 | B6: A005 | C6: 2485 | D6: 118 | E6: 293225 | F6: 598917 | G6: 95000 | H6: -400692 | I6: 650000 | J6: 0.167 | K6: 12 | L6: 0.9839 | M6: Budget
A7: 45689 | B7: A001 | C7: 56343.6 | D7: 88 | E7: 4958237 | F7: 1100749 | G7: 150000 | H7: 3707488 | I7: 60000 | J7: 0.4658 | K7: 6 | L7: 0.9911 | M7: Budget
A8: 45689 | B8: A002 | C8: 3996 | D8: 81 | E8: 323676 | F8: 107787 | G8: 42000 | H8: 173889 | I8: 8000 | J8: 0.0793 | K8: 6 | L8: 0.9911 | M8: Budget
A9: 45689 | B9: A003 | C9: 2237.8 | D9: 81 | E9: 181259 | F9: 64161 | G9: 30000 | H9: 87098 | I9: 8000 | J9: 0.0793 | K9: 6 | L9: 0.9911 | M9: Budget
A10: 45689 | B10: A004 | C10: 12540 | D10: 42.1 | E10: 527934 | F10: 285208 | G10: 65000 | H10: 177726 | I10: 175000 | J10: 0.311 | K10: 6 | L10: 0.9911 | M10: Budget
A11: 45689 | B11: A005 | C11: 2473 | D11: 118 | E11: 291809 | F11: 598053 | G11: 95000 | H11: -401244 | I11: 650000 | J11: 0.184 | K11: 12 | L11: 0.9821 | M11: Budget
A12: 45717 | B12: A001 | C12: 58449.6 | D12: 82 | E12: 4792867 | F12: 1117597 | G12: 150000 | H12: 3525270 | I12: 60000 | J12: 0.4365 | K12: 6 | L12: 0.9919 | M12: Budget
A13: 45717 | B13: A002 | C13: 6678 | D13: 75 | E13: 500850 | F13: 116370 | G13: 42000 | H13: 342480 | I13: 30000 | J13: 0.1197 | K13: 2 | L13: 0.9973 | M13: Budget
... A121: 46357 | B121: A005 | C121: 8035.2 | D121: 118 | E121: 948154 | F121: 998534 | G121: 95000 | H121: -145381 | I121: 420000 | J121: 0.54 | K121: 12 | L121: 0.9839 | M121: Budget

Sheet 05_PQ_Forecast
A1: month | B1: asset_id | C1: production_mwh | D1: realized_price_eur_mwh | E1: revenue_eur | F1: direct_opex_eur | G1: allocated_overhead_eur | H1: ebitda_eur | I1: capex_eur | J1: utilization_pct | K1: downtime_hours | L1: availability_pct | M1: Scenario
A2: 45658 | B2: A001 | C2: 64359.9 | D2: 86.48 | E2: 5565844 | F2: 1258148 | G2: 156000 | H2: 4151696 | I2: 64800 | J2: 0.4806 | K2: 18 | L2: 0.9758 | M2: Forecast
A3: 45658 | B3: A002 | C3: 3102.5 | D3: 84.15 | E3: 261073 | F3: 107938 | G3: 43050 | H3: 110085 | I3: 8320 | J3: 0.0556 | K3: 3 | L3: 0.996 | M3: Forecast
A4: 45658 | B4: A003 | C4: 1737.4 | D4: 84.15 | E4: 146201 | F4: 64359 | G4: 30750 | H4: 51092 | I4: 8320 | J4: 0.0556 | K4: 3 | L4: 0.996 | M4: Forecast
A5: 45658 | B5: A004 | C5: 11389 | D5: 42.38 | E5: 482679 | F5: 304810 | G5: 67600 | H5: 110269 | I5: 189000 | J5: 0.2551 | K5: 11 | L5: 0.9852 | M5: Forecast
A6: 45658 | B6: A005 | C6: 1814 | D6: 118 | E6: 214054 | F6: 676776 | G6: 100700 | H6: -563422 | I6: 598000 | J6: 0.1219 | K6: 28 | L6: 0.9624 | M6: Forecast
A7: 45689 | B7: A001 | C7: 54498.5 | D7: 82.72 | E7: 4508114 | F7: 1172297 | G7: 156000 | H7: 3179816 | I7: 64800 | J7: 0.4505 | K7: 18 | L7: 0.9732 | M7: Forecast
A8: 45689 | B8: A002 | C8: 4049.8 | D8: 80.19 | E8: 324757 | F8: 111021 | G8: 43050 | H8: 170687 | I8: 8320 | J8: 0.0804 | K8: 7 | L8: 0.9896 | M8: Forecast
A9: 45689 | B9: A003 | C9: 2267.9 | D9: 80.19 | E9: 181864 | F9: 66086 | G9: 30750 | H9: 85029 | I9: 8320 | J9: 0.0804 | K9: 7 | L9: 0.9896 | M9: Forecast
A10: 45689 | B10: A004 | C10: 11837.8 | D10: 42.94 | E10: 508337 | F10: 306599 | G10: 67600 | H10: 134138 | I10: 189000 | J10: 0.2936 | K10: 11 | L10: 0.9836 | M10: Forecast
A11: 45689 | B11: A005 | C11: 1805.3 | D11: 118 | E11: 213021 | F11: 675800 | G11: 100700 | H11: -563479 | I11: 598000 | J11: 0.1343 | K11: 28 | L11: 0.9583 | M11: Forecast
A12: 45717 | B12: A001 | C12: 56636.7 | D12: 77.08 | E12: 4365558 | F12: 1190241 | G12: 156000 | H12: 3019317 | I12: 64800 | J12: 0.4229 | K12: 18 | L12: 0.9758 | M12: Forecast
A13: 45717 | B13: A002 | C13: 6769 | D13: 74.25 | E13: 502601 | F13: 119861 | G13: 43050 | H13: 339690 | I13: 31200 | J13: 0.1213 | K13: 3 | L13: 0.996 | M13: Forecast
... A121: 46357 | B121: A005 | C121: 7231.7 | D121: 118 | E121: 853338 | F121: 1088402 | G121: 100700 | H121: -335764 | I121: 462000 | J121: 0.486 | K121: 28 | L121: 0.9624 | M121: Forecast

Sheet 06_Calculations
A1: Portfolio Performance Summary
A3: Metric | B3: Actual | C3: Budget | D3: Forecast | E3: Actual vs Budget | F3: Actual vs Budget % | G3: Forecast vs Budget | H3: Forecast vs Budget %
A4: Revenue | B4: =SUMIFS(fpna_monthly_combined[revenue_eur],fpna_monthly_combined[Scenario],"Actual") -> 136797930 | C4: =SUMIFS(fpna_monthly_combined[revenue_eur],fpna_monthly_combined[Scenario],"Budget") -> 147328639 | D4: =SUMIFS(fpna_monthly_combined[revenue_eur],fpna_monthly_combined[Scenario],"Forecast") -> 139428477 | E4: =B4-C4 -> -10530709 | F4: =IFERROR(E4/C4,0) -> -0.071477678 | G4: =D4-C4 -> -7900162 | H4: =IFERROR(G4/C4,0) -> -0.053622718
A5: Direct opex | B5: =SUMIFS(fpna_monthly_combined[direct_opex_eur],fpna_monthly_combined[Scenario],"Actual") -> 64247970 | C5: =SUMIFS(fpna_monthly_combined[direct_opex_eur],fpna_monthly_combined[Scenario],"Budget") -> 56918774 | D5: =SUMIFS(fpna_monthly_combined[direct_opex_eur],fpna_monthly_combined[Scenario],"Forecast") -> 61270546 | E5: =B5-C5 -> 7329196 | F5: =IFERROR(E5/C5,0) -> 0.12876588 | G5: =D5-C5 -> 4351772 | H5: =IFERROR(G5/C5,0) -> 0.076455828
A6: Allocated overhead | B6: =SUMIFS(fpna_monthly_combined[allocated_overhead_eur],fpna_monthly_combined[Scenario],"Actual") -> 9554400 | C6: =SUMIFS(fpna_monthly_combined[allocated_overhead_eur],fpna_monthly_combined[Scenario],"Budget") -> 9168000 | D6: =SUMIFS(fpna_monthly_combined[allocated_overhead_eur],fpna_monthly_combined[Scenario],"Forecast") -> 9554400 | E6: =B6-C6 -> 386400 | F6: =IFERROR(E6/C6,0) -> 0.042146597 | G6: =D6-C6 -> 386400 | H6: =IFERROR(G6/C6,0) -> 0.042146597
A7: EBITDA | B7: =SUMIFS(fpna_monthly_combined[ebitda_eur],fpna_monthly_combined[Scenario],"Actual") -> 62995562 | C7: =SUMIFS(fpna_monthly_combined[ebitda_eur],fpna_monthly_combined[Scenario],"Budget") -> 81241865 | D7: =SUMIFS(fpna_monthly_combined[ebitda_eur],fpna_monthly_combined[Scenario],"Forecast") -> 68603524 | E7: =B7-C7 -> -18246303 | F7: =IFERROR(E7/C7,0) -> -0.22459237 | G7: =D7-C7 -> -12638341 | H7: =IFERROR(G7/C7,0) -> -0.15556439
A8: Capex | B8: =SUMIFS(fpna_monthly_combined[capex_eur],fpna_monthly_combined[Scenario],"Actual") -> 19631695 | C8: =SUMIFS(fpna_monthly_combined[capex_eur],fpna_monthly_combined[Scenario],"Budget") -> 19170000 | D8: =SUMIFS(fpna_monthly_combined[capex_eur],fpna_monthly_combined[Scenario],"Forecast") -> 19366000 | E8: =B8-C8 -> 461695 | F8: =IFERROR(E8/C8,0) -> 0.024084246 | G8: =D8-C8 -> 196000 | H8: =IFERROR(G8/C8,0) -> 0.010224309
A9: Production MWh | B9: =SUMIFS(fpna_monthly_combined[production_mwh],fpna_monthly_combined[Scenario],"Actual") -> 1976268.5 | C9: =SUMIFS(fpna_monthly_combined[production_mwh],fpna_monthly_combined[Scenario],"Budget") -> 2008387.4 | D9: =SUMIFS(fpna_monthly_combined[production_mwh],fpna_monthly_combined[Scenario],"Forecast") -> 1983669.7 | E9: =B9-C9 -> -32118.9 | F9: =IFERROR(E9/C9,0) -> -0.015992383 | G9: =D9-C9 -> -24717.7 | H9: =IFERROR(G9/C9,0) -> -0.012307237
A10: Downtime hours | B10: =SUMIFS(fpna_monthly_combined[downtime_hours],fpna_monthly_combined[Scenario],"Actual") -> 1847 | C10: =SUMIFS(fpna_monthly_combined[downtime_hours],fpna_monthly_combined[Scenario],"Budget") -> 900 | D10: =SUMIFS(fpna_monthly_combined[downtime_hours],fpna_monthly_combined[Scenario],"Forecast") -> 1692 | E10: =B10-C10 -> 947 | F10: =IFERROR(E10/C10,0) -> 1.0522222 | G10: =D10-C10 -> 792 | H10: =IFERROR(G10/C10,0) -> 0.88
A13: Asset Performance Summary
A15: Asset | B15: Technology | C15: Actual Revenue | D15: Budget Revenue | E15: Revenue Var | F15: Actual EBITDA | G15: Budget EBITDA | H15: EBITDA Var | I15: EBITDA Var % | J15: Actual Downtime | K15: Budget Downtime | L15: Downtime Var
A16: {=_xlfn._xlws.SORT(_xlfn.UNIQUE(fpna_monthly_combined[asset_name]))} -> Brabant Solar C | B16: =_xlfn.XLOOKUP(A16,fpna_monthly_combined[asset_name],fpna_monthly_combined[technology],"") -> Solar PV | C16: =SUMIFS(fpna_monthly_combined[revenue_eur],fpna_monthly_combined[asset_name],$A16,fpna_monthly_combined[Scenario],"Actual") -> 6344855 | D16: =SUMIFS(fpna_monthly_combined[revenue_eur],fpna_monthly_combined[asset_name],$A16,fpna_monthly_combined[Scenario],"Budget") -> 6399685 | E16: =C16-D16 -> -54830 | F16: =SUMIFS(fpna_monthly_combined[ebitda_eur],fpna_monthly_combined[asset_name],$A16,fpna_monthly_combined[Scenario],"Actual") -> 3862374 | G16: =SUMIFS(fpna_monthly_combined[ebitda_eur],fpna_monthly_combined[asset_name],$A16,fpna_monthly_combined[Scenario],"Budget") -> 3988200 | H16: =F16-G16 -> -125826 | I16: =IF(G16<0,"n.m.",IFERROR(H16/G16,0)) -> -0.031549571 | J16: =SUMIFS(fpna_monthly_combined[downtime_hours],fpna_monthly_combined[asset_name],$A16,fpna_monthly_combined[Scenario],"Actual") -> 106 | K16: =SUMIFS(fpna_monthly_combined[downtime_hours],fpna_monthly_combined[asset_name],$A16,fpna_monthly_combined[Scenario],"Budget") -> 64 | L16: =J16-K16 -> 42
A17: Flevoland Solar B | B17: =_xlfn.XLOOKUP(A17,fpna_monthly_combined[asset_name],fpna_monthly_combined[technology],"") -> Solar PV | C17: =SUMIFS(fpna_monthly_combined[revenue_eur],fpna_monthly_combined[asset_name],$A17,fpna_monthly_combined[Scenario],"Actual") -> 11560396 | D17: =SUMIFS(fpna_monthly_combined[revenue_eur],fpna_monthly_combined[asset_name],$A17,fpna_monthly_combined[Scenario],"Budget") -> 11428015 | E17: =C17-D17 -> 132381 | F17: =SUMIFS(fpna_monthly_combined[ebitda_eur],fpna_monthly_combined[asset_name],$A17,fpna_monthly_combined[Scenario],"Actual") -> 7599197 | G17: =SUMIFS(fpna_monthly_combined[ebitda_eur],fpna_monthly_combined[asset_name],$A17,fpna_monthly_combined[Scenario],"Budget") -> 7562362 | H17: =F17-G17 -> 36835 | I17: =IF(G17<0,"n.m.",IFERROR(H17/G17,0)) -> 0.0048708327 | J17: =SUMIFS(fpna_monthly_combined[downtime_hours],fpna_monthly_combined[asset_name],$A17,fpna_monthly_combined[Scenario],"Actual") -> 104 | K17: =SUMIFS(fpna_monthly_combined[downtime_hours],fpna_monthly_combined[asset_name],$A17,fpna_monthly_combined[Scenario],"Budget") -> 64 | L17: =J17-K17 -> 40
A18: Groningen Hydrogen Pilot E | B18: =_xlfn.XLOOKUP(A18,fpna_monthly_combined[asset_name],fpna_monthly_combined[technology],"") -> Hydrogen pilot | C18: =SUMIFS(fpna_monthly_combined[revenue_eur],fpna_monthly_combined[asset_name],$A18,fpna_monthly_combined[Scenario],"Actual") -> 11235894 | D18: =SUMIFS(fpna_monthly_combined[revenue_eur],fpna_monthly_combined[asset_name],$A18,fpna_monthly_combined[Scenario],"Budget") -> 14973349 | E18: =C18-D18 -> -3737455 | F18: =SUMIFS(fpna_monthly_combined[ebitda_eur],fpna_monthly_combined[asset_name],$A18,fpna_monthly_combined[Scenario],"Actual") -> -14367559 | G18: =SUMIFS(fpna_monthly_combined[ebitda_eur],fpna_monthly_combined[asset_name],$A18,fpna_monthly_combined[Scenario],"Budget") -> -6522932 | H18: =F18-G18 -> -7844627 | I18: =IF(G18<0,"n.m.",IFERROR(H18/G18,0)) -> n.m. | J18: =SUMIFS(fpna_monthly_combined[downtime_hours],fpna_monthly_combined[asset_name],$A18,fpna_monthly_combined[Scenario],"Actual") -> 866 | K18: =SUMIFS(fpna_monthly_combined[downtime_hours],fpna_monthly_combined[asset_name],$A18,fpna_monthly_combined[Scenario],"Budget") -> 380 | L18: =J18-K18 -> 486
A19: Noordzee Wind A | B19: =_xlfn.XLOOKUP(A19,fpna_monthly_combined[asset_name],fpna_monthly_combined[technology],"") -> Offshore wind | C19: =SUMIFS(fpna_monthly_combined[revenue_eur],fpna_monthly_combined[asset_name],$A19,fpna_monthly_combined[Scenario],"Actual") -> 89440037 | D19: =SUMIFS(fpna_monthly_combined[revenue_eur],fpna_monthly_combined[asset_name],$A19,fpna_monthly_combined[Scenario],"Budget") -> 98288490 | E19: =C19-D19 -> -8848453 | F19: =SUMIFS(fpna_monthly_combined[ebitda_eur],fpna_monthly_combined[asset_name],$A19,fpna_monthly_combined[Scenario],"Actual") -> 57157076 | G19: =SUMIFS(fpna_monthly_combined[ebitda_eur],fpna_monthly_combined[asset_name],$A19,fpna_monthly_combined[Scenario],"Budget") -> 68682975 | H19: =F19-G19 -> -11525899 | I19: =IF(G19<0,"n.m.",IFERROR(H19/G19,0)) -> -0.16781304 | J19: =SUMIFS(fpna_monthly_combined[downtime_hours],fpna_monthly_combined[asset_name],$A19,fpna_monthly_combined[Scenario],"Actual") -> 439 | K19: =SUMIFS(fpna_monthly_combined[downtime_hours],fpna_monthly_combined[asset_name],$A19,fpna_monthly_combined[Scenario],"Budget") -> 200 | L19: =J19-K19 -> 239
A20: Rotterdam Battery D | B20: =_xlfn.XLOOKUP(A20,fpna_monthly_combined[asset_name],fpna_monthly_combined[technology],"") -> Battery storage | C20: =SUMIFS(fpna_monthly_combined[revenue_eur],fpna_monthly_combined[asset_name],$A20,fpna_monthly_combined[Scenario],"Actual") -> 18216748 | D20: =SUMIFS(fpna_monthly_combined[revenue_eur],fpna_monthly_combined[asset_name],$A20,fpna_monthly_combined[Scenario],"Budget") -> 16239100 | E20: =C20-D20 -> 1977648 | F20: =SUMIFS(fpna_monthly_combined[ebitda_eur],fpna_monthly_combined[asset_name],$A20,fpna_monthly_combined[Scenario],"Actual") -> 8744474 | G20: =SUMIFS(fpna_monthly_combined[ebitda_eur],fpna_monthly_combined[asset_name],$A20,fpna_monthly_combined[Scenario],"Budget") -> 7531260 | H20: =F20-G20 -> 1213214 | I20: =IF(G20<0,"n.m.",IFERROR(H20/G20,0)) -> 0.16109044 | J20: =SUMIFS(fpna_monthly_combined[downtime_hours],fpna_monthly_combined[asset_name],$A20,fpna_monthly_combined[Scenario],"Actual") -> 332 | K20: =SUMIFS(fpna_monthly_combined[downtime_hours],fpna_monthly_combined[asset_name],$A20,fpna_monthly_combined[Scenario],"Budget") -> 192 | L20: =J20-K20 -> 140
A24: Monthly Trend Summary
A26: Month | B26: Actual Revenue | C26: Budget Revenue | D26: Forecast Revenue | E26: Actual EBITDA | F26: Budget EBITDA | G26: Forecast EBITDA | H26: Revenue Var | I26: EBITDA Var
A27: {=_xlfn._xlws.SORT(_xlfn.UNIQUE(fpna_monthly_combined[month]))} -> 45658 | B27: =SUMIFS(fpna_monthly_combined[revenue_eur], fpna_monthly_combined[month], $A27, fpna_monthly_combined[Scenario], "Actual") -> 6212435 | C27: =SUMIFS(fpna_monthly_combined[revenue_eur], fpna_monthly_combined[month], $A27, fpna_monthly_combined[Scenario], "Budget") -> 7317462 | D27: =SUMIFS(fpna_monthly_combined[revenue_eur], fpna_monthly_combined[month], $A27, fpna_monthly_combined[Scenario], "Forecast") -> 6669851 | E27: =SUMIFS(fpna_monthly_combined[ebitda_eur], fpna_monthly_combined[month], $A27, fpna_monthly_combined[Scenario], "Actual") -> 3329129 | F27: =SUMIFS(fpna_monthly_combined[ebitda_eur], fpna_monthly_combined[month], $A27, fpna_monthly_combined[Scenario], "Budget") -> 4704361 | G27: =SUMIFS(fpna_monthly_combined[ebitda_eur], fpna_monthly_combined[month], $A27, fpna_monthly_combined[Scenario], "Forecast") -> 3859720 | H27: =B27-C27 -> -1105027 | I27: =E27-F27 -> -1375232
A28: 45689 | B28: =SUMIFS(fpna_monthly_combined[revenue_eur], fpna_monthly_combined[month], $A28, fpna_monthly_combined[Scenario], "Actual") -> 5646508 | C28: =SUMIFS(fpna_monthly_combined[revenue_eur], fpna_monthly_combined[month], $A28, fpna_monthly_combined[Scenario], "Budget") -> 6282915 | D28: =SUMIFS(fpna_monthly_combined[revenue_eur], fpna_monthly_combined[month], $A28, fpna_monthly_combined[Scenario], "Forecast") -> 5736093 | E28: =SUMIFS(fpna_monthly_combined[ebitda_eur], fpna_monthly_combined[month], $A28, fpna_monthly_combined[Scenario], "Actual") -> 2800724 | F28: =SUMIFS(fpna_monthly_combined[ebitda_eur], fpna_monthly_combined[month], $A28, fpna_monthly_combined[Scenario], "Budget") -> 3744957 | G28: =SUMIFS(fpna_monthly_combined[ebitda_eur], fpna_monthly_combined[month], $A28, fpna_monthly_combined[Scenario], "Forecast") -> 3006191 | H28: =B28-C28 -> -636407 | I28: =E28-F28 -> -944233
A29: 45717 | B29: =SUMIFS(fpna_monthly_combined[revenue_eur], fpna_monthly_combined[month], $A29, fpna_monthly_combined[Scenario], "Actual") -> 5936102 | C29: =SUMIFS(fpna_monthly_combined[revenue_eur], fpna_monthly_combined[month], $A29, fpna_monthly_combined[Scenario], "Budget") -> 6358586 | D29: =SUMIFS(fpna_monthly_combined[revenue_eur], fpna_monthly_combined[month], $A29, fpna_monthly_combined[Scenario], "Forecast") -> 5827983 | E29: =SUMIFS(fpna_monthly_combined[ebitda_eur], fpna_monthly_combined[month], $A29, fpna_monthly_combined[Scenario], "Actual") -> 2980174 | F29: =SUMIFS(fpna_monthly_combined[ebitda_eur], fpna_monthly_combined[month], $A29, fpna_monthly_combined[Scenario], "Budget") -> 3758716 | G29: =SUMIFS(fpna_monthly_combined[ebitda_eur], fpna_monthly_combined[month], $A29, fpna_monthly_combined[Scenario], "Forecast") -> 3030246 | H29: =B29-C29 -> -422484 | I29: =E29-F29 -> -778542
A30: 45748 | B30: =SUMIFS(fpna_monthly_combined[revenue_eur], fpna_monthly_combined[month], $A30, fpna_monthly_combined[Scenario], "Actual") -> 4702421 | C30: =SUMIFS(fpna_monthly_combined[revenue_eur], fpna_monthly_combined[month], $A30, fpna_monthly_combined[Scenario], "Budget") -> 5386728 | D30: =SUMIFS(fpna_monthly_combined[revenue_eur], fpna_monthly_combined[month], $A30, fpna_monthly_combined[Scenario], "Forecast") -> 4956826 | E30: =SUMIFS(fpna_monthly_combined[ebitda_eur], fpna_monthly_combined[month], $A30, fpna_monthly_combined[Scenario], "Actual") -> 1491709 | F30: =SUMIFS(fpna_monthly_combined[ebitda_eur], fpna_monthly_combined[month], $A30, fpna_monthly_combined[Scenario], "Budget") -> 2729398 | G30: =SUMIFS(fpna_monthly_combined[ebitda_eur], fpna_monthly_combined[month], $A30, fpna_monthly_combined[Scenario], "Forecast") -> 2097521 | H30: =B30-C30 -> -684307 | I30: =E30-F30 -> -1237689
A31: 45778 | B31: =SUMIFS(fpna_monthly_combined[revenue_eur], fpna_monthly_combined[month], $A31, fpna_monthly_combined[Scenario], "Actual") -> 4293722 | C31: =SUMIFS(fpna_monthly_combined[revenue_eur], fpna_monthly_combined[month], $A31, fpna_monthly_combined[Scenario], "Budget") -> 5018343 | D31: =SUMIFS(fpna_monthly_combined[revenue_eur], fpna_monthly_combined[month], $A31, fpna_monthly_combined[Scenario], "Forecast") -> 4632839 | E31: =SUMIFS(fpna_monthly_combined[ebitda_eur], fpna_monthly_combined[month], $A31, fpna_monthly_combined[Scenario], "Actual") -> 1285300 | F31: =SUMIFS(fpna_monthly_combined[ebitda_eur], fpna_monthly_combined[month], $A31, fpna_monthly_combined[Scenario], "Budget") -> 2473396 | G31: =SUMIFS(fpna_monthly_combined[ebitda_eur], fpna_monthly_combined[month], $A31, fpna_monthly_combined[Scenario], "Forecast") -> 1891969 | H31: =B31-C31 -> -724621 | I31: =E31-F31 -> -1188096
A32: 45809 | B32: =SUMIFS(fpna_monthly_combined[revenue_eur], fpna_monthly_combined[month], $A32, fpna_monthly_combined[Scenario], "Actual") -> 3972882 | C32: =SUMIFS(fpna_monthly_combined[revenue_eur], fpna_monthly_combined[month], $A32, fpna_monthly_combined[Scenario], "Budget") -> 4539130 | D32: =SUMIFS(fpna_monthly_combined[revenue_eur], fpna_monthly_combined[month], $A32, fpna_monthly_combined[Scenario], "Forecast") -> 4201265 | E32: =SUMIFS(fpna_monthly_combined[ebitda_eur], fpna_monthly_combined[month], $A32, fpna_monthly_combined[Scenario], "Actual") -> 1170387 | F32: =SUMIFS(fpna_monthly_combined[ebitda_eur], fpna_monthly_combined[month], $A32, fpna_monthly_combined[Scenario], "Budget") -> 2020341 | G32: =SUMIFS(fpna_monthly_combined[ebitda_eur], fpna_monthly_combined[month], $A32, fpna_monthly_combined[Scenario], "Forecast") -> 1487792 | H32: =B32-C32 -> -566248 | I32: =E32-F32 -> -849954
A33: 45839 | B33: =SUMIFS(fpna_monthly_combined[revenue_eur], fpna_monthly_combined[month], $A33, fpna_monthly_combined[Scenario], "Actual") -> 4165986 | C33: =SUMIFS(fpna_monthly_combined[revenue_eur], fpna_monthly_combined[month], $A33, fpna_monthly_combined[Scenario], "Budget") -> 4542307 | D33: =SUMIFS(fpna_monthly_combined[revenue_eur], fpna_monthly_combined[month], $A33, fpna_monthly_combined[Scenario], "Forecast") -> 4207456 | E33: =SUMIFS(fpna_monthly_combined[ebitda_eur], fpna_monthly_combined[month], $A33, fpna_monthly_combined[Scenario], "Actual") -> 1336141 | F33: =SUMIFS(fpna_monthly_combined[ebitda_eur], fpna_monthly_combined[month], $A33, fpna_monthly_combined[Scenario], "Budget") -> 1991778 | G33: =SUMIFS(fpna_monthly_combined[ebitda_eur], fpna_monthly_combined[month], $A33, fpna_monthly_combined[Scenario], "Forecast") -> 1458536 | H33: =B33-C33 -> -376321 | I33: =E33-F33 -> -655637
A34: 45870 | B34: =SUMIFS(fpna_monthly_combined[revenue_eur], fpna_monthly_combined[month], $A34, fpna_monthly_combined[Scenario], "Actual") -> 4127765 | C34: =SUMIFS(fpna_monthly_combined[revenue_eur], fpna_monthly_combined[month], $A34, fpna_monthly_combined[Scenario], "Budget") -> 4826686 | D34: =SUMIFS(fpna_monthly_combined[revenue_eur], fpna_monthly_combined[month], $A34, fpna_monthly_combined[Scenario], "Forecast") -> 4464088 | E34: =SUMIFS(fpna_monthly_combined[ebitda_eur], fpna_monthly_combined[month], $A34, fpna_monthly_combined[Scenario], "Actual") -> 1253877 | F34: =SUMIFS(fpna_monthly_combined[ebitda_eur], fpna_monthly_combined[month], $A34, fpna_monthly_combined[Scenario], "Budget") -> 2241972 | G34: =SUMIFS(fpna_monthly_combined[ebitda_eur], fpna_monthly_combined[month], $A34, fpna_monthly_combined[Scenario], "Forecast") -> 1677316 | H34: =B34-C34 -> -698921 | I34: =E34-F34 -> -988095
A35: 45901 | B35: =SUMIFS(fpna_monthly_combined[revenue_eur], fpna_monthly_combined[month], $A35, fpna_monthly_combined[Scenario], "Actual") -> 4879266 | C35: =SUMIFS(fpna_monthly_combined[revenue_eur], fpna_monthly_combined[month], $A35, fpna_monthly_combined[Scenario], "Budget") -> 5358944 | D35: =SUMIFS(fpna_monthly_combined[revenue_eur], fpna_monthly_combined[month], $A35, fpna_monthly_combined[Scenario], "Forecast") -> 4942570 | E35: =SUMIFS(fpna_monthly_combined[ebitda_eur], fpna_monthly_combined[month], $A35, fpna_monthly_combined[Scenario], "Actual") -> 1940431 | F35: =SUMIFS(fpna_monthly_combined[ebitda_eur], fpna_monthly_combined[month], $A35, fpna_monthly_combined[Scenario], "Budget") -> 2739413 | G35: =SUMIFS(fpna_monthly_combined[ebitda_eur], fpna_monthly_combined[month], $A35, fpna_monthly_combined[Scenario], "Forecast") -> 2117661 | H35: =B35-C35 -> -479678 | I35: =E35-F35 -> -798982
A36: 45931 | B36: =SUMIFS(fpna_monthly_combined[revenue_eur], fpna_monthly_combined[month], $A36, fpna_monthly_combined[Scenario], "Actual") -> 5586206 | C36: =SUMIFS(fpna_monthly_combined[revenue_eur], fpna_monthly_combined[month], $A36, fpna_monthly_combined[Scenario], "Budget") -> 6302300 | D36: =SUMIFS(fpna_monthly_combined[revenue_eur], fpna_monthly_combined[month], $A36, fpna_monthly_combined[Scenario], "Forecast") -> 5786098 | E36: =SUMIFS(fpna_monthly_combined[ebitda_eur], fpna_monthly_combined[month], $A36, fpna_monthly_combined[Scenario], "Actual") -> 2463792 | F36: =SUMIFS(fpna_monthly_combined[ebitda_eur], fpna_monthly_combined[month], $A36, fpna_monthly_combined[Scenario], "Budget") -> 3477180 | G36: =SUMIFS(fpna_monthly_combined[ebitda_eur], fpna_monthly_combined[month], $A36, fpna_monthly_combined[Scenario], "Forecast") -> 2739918 | H36: =B36-C36 -> -716094 | I36: =E36-F36 -> -1013388
A37: 45962 | B37: =SUMIFS(fpna_monthly_combined[revenue_eur], fpna_monthly_combined[month], $A37, fpna_monthly_combined[Scenario], "Actual") -> 5794661 | C37: =SUMIFS(fpna_monthly_combined[revenue_eur], fpna_monthly_combined[month], $A37, fpna_monthly_combined[Scenario], "Budget") -> 7053556 | D37: =SUMIFS(fpna_monthly_combined[revenue_eur], fpna_monthly_combined[month], $A37, fpna_monthly_combined[Scenario], "Forecast") -> 6476848 | E37: =SUMIFS(fpna_monthly_combined[ebitda_eur], fpna_monthly_combined[month], $A37, fpna_monthly_combined[Scenario], "Actual") -> 2580557 | F37: =SUMIFS(fpna_monthly_combined[ebitda_eur], fpna_monthly_combined[month], $A37, fpna_monthly_combined[Scenario], "Budget") -> 4299359 | G37: =SUMIFS(fpna_monthly_combined[ebitda_eur], fpna_monthly_combined[month], $A37, fpna_monthly_combined[Scenario], "Forecast") -> 3505275 | H37: =B37-C37 -> -1258895 | I37: =E37-F37 -> -1718802
A38: 45992 | B38: =SUMIFS(fpna_monthly_combined[revenue_eur], fpna_monthly_combined[month], $A38, fpna_monthly_combined[Scenario], "Actual") -> 7362190 | C38: =SUMIFS(fpna_monthly_combined[revenue_eur], fpna_monthly_combined[month], $A38, fpna_monthly_combined[Scenario], "Budget") -> 8116782 | D38: =SUMIFS(fpna_monthly_combined[revenue_eur], fpna_monthly_combined[month], $A38, fpna_monthly_combined[Scenario], "Forecast") -> 7446401 | E38: =SUMIFS(fpna_monthly_combined[ebitda_eur], fpna_monthly_combined[month], $A38, fpna_monthly_combined[Scenario], "Actual") -> 4219638 | F38: =SUMIFS(fpna_monthly_combined[ebitda_eur], fpna_monthly_combined[month], $A38, fpna_monthly_combined[Scenario], "Budget") -> 5275795 | G38: =SUMIFS(fpna_monthly_combined[ebitda_eur], fpna_monthly_combined[month], $A38, fpna_monthly_combined[Scenario], "Forecast") -> 4380315 | H38: =B38-C38 -> -754592 | I38: =E38-F38 -> -1056157
A39: 46023 | B39: =SUMIFS(fpna_monthly_combined[revenue_eur], fpna_monthly_combined[month], $A39, fpna_monthly_combined[Scenario], "Actual") -> 7330978 | C39: =SUMIFS(fpna_monthly_combined[revenue_eur], fpna_monthly_combined[month], $A39, fpna_monthly_combined[Scenario], "Budget") -> 7690596 | D39: =SUMIFS(fpna_monthly_combined[revenue_eur], fpna_monthly_combined[month], $A39, fpna_monthly_combined[Scenario], "Forecast") -> 7366174 | E39: =SUMIFS(fpna_monthly_combined[ebitda_eur], fpna_monthly_combined[month], $A39, fpna_monthly_combined[Scenario], "Actual") -> 4221537 | F39: =SUMIFS(fpna_monthly_combined[ebitda_eur], fpna_monthly_combined[month], $A39, fpna_monthly_combined[Scenario], "Budget") -> 4838970 | G39: =SUMIFS(fpna_monthly_combined[ebitda_eur], fpna_monthly_combined[month], $A39, fpna_monthly_combined[Scenario], "Forecast") -> 4326375 | H39: =B39-C39 -> -359618 | I39: =E39-F39 -> -617433
... A50: 46357 | B50: =SUMIFS(fpna_monthly_combined[revenue_eur], fpna_monthly_combined[month], $A50, fpna_monthly_combined[Scenario], "Actual") -> 8176669 | C50: =SUMIFS(fpna_monthly_combined[revenue_eur], fpna_monthly_combined[month], $A50, fpna_monthly_combined[Scenario], "Budget") -> 8495859 | D50: =SUMIFS(fpna_monthly_combined[revenue_eur], fpna_monthly_combined[month], $A50, fpna_monthly_combined[Scenario], "Forecast") -> 8250976 | E50: =SUMIFS(fpna_monthly_combined[ebitda_eur], fpna_monthly_combined[month], $A50, fpna_monthly_combined[Scenario], "Actual") -> 4821136 | F50: =SUMIFS(fpna_monthly_combined[ebitda_eur], fpna_monthly_combined[month], $A50, fpna_monthly_combined[Scenario], "Budget") -> 5435631 | G50: =SUMIFS(fpna_monthly_combined[ebitda_eur], fpna_monthly_combined[month], $A50, fpna_monthly_combined[Scenario], "Forecast") -> 4984624 | H50: =B50-C50 -> -319190 | I50: =E50-F50 -> -614495

Sheet 07_Variance_Analysis
A1: EBITDA Variance Bridge
A3: Driver | B3: Amount
A4: Budget | B4: ='06_Calculations'!C7 -> 81241865
A5: Price | B5: =SUMIFS(variance_drivers[variance_eur],variance_drivers[variance_type],"Price") -> -6250514
A6: Volume | B6: =SUMIFS(variance_drivers[variance_eur],variance_drivers[variance_type],"Volume") -> -1037482
A7: Downtime | B7: =SUMIFS(variance_drivers[variance_eur],variance_drivers[variance_type],"Downtime") -> -1344047
A8: Ramp-up | B8: =SUMIFS(variance_drivers[variance_eur],variance_drivers[variance_type],"Ramp-up") -> -1898367
A9: Opex | B9: =SUMIFS(variance_drivers[variance_eur],variance_drivers[variance_type],"Opex") -> -7329196
A10: Timing/Mix | B10: =SUMIFS(variance_drivers[variance_eur],variance_drivers[variance_type],"Timing/Mix") -> -386689
A11: Actual | B11: ='06_Calculations'!B7 -> 62995562
A12: Total variance | B12: =SUM(B5:B10) -> -18246295
A13: Bridge check | B13: =B11-(B4+B12) -> -8

Sheet 08_Scenario_Model
A1: Scenario Model
A3: Selected scenario | B3: Base
A6: Technology | B6: Price index | C6: Volume factor | D6: Opex inflation | E6: Downtime factor | F6: Budget Revenue | G6: Scenario Revenue | H6: Revenue Delta | I6: Budget EBITDA | J6: Scenario EBITDA | K6: EBITDA Delta | M6: Metric | N6: Revenue | O6: EBITDA
A7: Offshore wind | B7: {=_xlfn.XLOOKUP($B$3&A7,assumptions[scenario]&assumptions[technology],assumptions[price_index])} -> 1.02 | C7: {=_xlfn.XLOOKUP($B$3&A7,assumptions[scenario]&assumptions[technology],assumptions[volume_factor])} -> 0.98 | D7: {=_xlfn.XLOOKUP($B$3&A7,assumptions[scenario]&assumptions[technology],assumptions[opex_inflation])} -> 0.055 | E7: {=_xlfn.XLOOKUP($B$3&A7,assumptions[scenario]&assumptions[technology],assumptions[downtime_factor])} -> 1.2 | F7: =SUMIFS(fpna_monthly_combined[revenue_eur],fpna_monthly_combined[technology],$A7,fpna_monthly_combined[Scenario],"Budget") -> 98288490 | G7: =F7*B7*C7 -> 98249175 | H7: =G7-F7 -> -39315.396 | I7: =SUMIFS(fpna_monthly_combined[ebitda_eur],fpna_monthly_combined[technology],$A7,fpna_monthly_combined[Scenario],"Budget") -> 68682975 | J7: =G7-(SUMIFS(fpna_monthly_combined[direct_opex_eur],fpna_monthly_combined[technology],$A7,fpna_monthly_combined[Scenario],"Budget")*(1+D7))-SUMIFS(fpna_monthly_combined[allocated_overhead_eur],fpna_monthly_combined[technology],$A7,fpna_monthly_combined[Scenario],"Budget") -> 67213353 | K7: =J7-I7 -> -1469621.9 | M7: Budget | N7: =F12 -> 147328639 | O7: =I12 -> 81241865
A8: Solar PV | B8: {=_xlfn.XLOOKUP($B$3&A8,assumptions[scenario]&assumptions[technology],assumptions[price_index])} -> 0.96 | C8: {=_xlfn.XLOOKUP($B$3&A8,assumptions[scenario]&assumptions[technology],assumptions[volume_factor])} -> 1.02 | D8: {=_xlfn.XLOOKUP($B$3&A8,assumptions[scenario]&assumptions[technology],assumptions[opex_inflation])} -> 0.045 | E8: {=_xlfn.XLOOKUP($B$3&A8,assumptions[scenario]&assumptions[technology],assumptions[downtime_factor])} -> 0.7 | F8: =SUMIFS(fpna_monthly_combined[revenue_eur],fpna_monthly_combined[technology],$A8,fpna_monthly_combined[Scenario],"Budget") -> 17827700 | G8: =F8*B8*C8 -> 17456884 | H8: =G8-F8 -> -370816.16 | I8: =SUMIFS(fpna_monthly_combined[ebitda_eur],fpna_monthly_combined[technology],$A8,fpna_monthly_combined[Scenario],"Budget") -> 11550562 | J8: =G8-(SUMIFS(fpna_monthly_combined[direct_opex_eur],fpna_monthly_combined[technology],$A8,fpna_monthly_combined[Scenario],"Budget")*(1+D8))-SUMIFS(fpna_monthly_combined[allocated_overhead_eur],fpna_monthly_combined[technology],$A8,fpna_monthly_combined[Scenario],"Budget") -> 10975039 | K8: =J8-I8 -> -575523.19 | M8: Scenario | N8: =G12 -> 1.4726326e+08 | O8: =J12 -> 78009663
A9: Battery storage | B9: {=_xlfn.XLOOKUP($B$3&A9,assumptions[scenario]&assumptions[technology],assumptions[price_index])} -> 1.12 | C9: {=_xlfn.XLOOKUP($B$3&A9,assumptions[scenario]&assumptions[technology],assumptions[volume_factor])} -> 1.06 | D9: {=_xlfn.XLOOKUP($B$3&A9,assumptions[scenario]&assumptions[technology],assumptions[opex_inflation])} -> 0.053 | E9: {=_xlfn.XLOOKUP($B$3&A9,assumptions[scenario]&assumptions[technology],assumptions[downtime_factor])} -> 1.05 | F9: =SUMIFS(fpna_monthly_combined[revenue_eur],fpna_monthly_combined[technology],$A9,fpna_monthly_combined[Scenario],"Budget") -> 16239100 | G9: =F9*B9*C9 -> 19279060 | H9: =G9-F9 -> 3039959.5 | I9: =SUMIFS(fpna_monthly_combined[ebitda_eur],fpna_monthly_combined[technology],$A9,fpna_monthly_combined[Scenario],"Budget") -> 7531260 | J9: =G9-(SUMIFS(fpna_monthly_combined[direct_opex_eur],fpna_monthly_combined[technology],$A9,fpna_monthly_combined[Scenario],"Budget")*(1+D9))-SUMIFS(fpna_monthly_combined[allocated_overhead_eur],fpna_monthly_combined[technology],$A9,fpna_monthly_combined[Scenario],"Budget") -> 10192384 | K9: =J9-I9 -> 2661124
A10: Hydrogen pilot | B10: {=_xlfn.XLOOKUP($B$3&A10,assumptions[scenario]&assumptions[technology],assumptions[price_index])} -> 1 | C10: {=_xlfn.XLOOKUP($B$3&A10,assumptions[scenario]&assumptions[technology],assumptions[volume_factor])} -> 0.82 | D10: {=_xlfn.XLOOKUP($B$3&A10,assumptions[scenario]&assumptions[technology],assumptions[opex_inflation])} -> 0.06 | E10: {=_xlfn.XLOOKUP($B$3&A10,assumptions[scenario]&assumptions[technology],assumptions[downtime_factor])} -> 1.3 | F10: =SUMIFS(fpna_monthly_combined[revenue_eur],fpna_monthly_combined[technology],$A10,fpna_monthly_combined[Scenario],"Budget") -> 14973349 | G10: =F10*B10*C10 -> 12278146 | H10: =G10-F10 -> -2695202.8 | I10: =SUMIFS(fpna_monthly_combined[ebitda_eur],fpna_monthly_combined[technology],$A10,fpna_monthly_combined[Scenario],"Budget") -> -6522932 | J10: =G10-(SUMIFS(fpna_monthly_combined[direct_opex_eur],fpna_monthly_combined[technology],$A10,fpna_monthly_combined[Scenario],"Budget")*(1+D10))-SUMIFS(fpna_monthly_combined[allocated_overhead_eur],fpna_monthly_combined[technology],$A10,fpna_monthly_combined[Scenario],"Budget") -> -10371113 | K10: =J10-I10 -> -3848180.7
A12: Total | F12: =SUM(F7:F10) -> 147328639 | G12: =SUM(G7:G10) -> 1.4726326e+08 | H12: =SUM(H7:H10) -> -65374.856 | I12: =SUM(I7:I10) -> 81241865 | J12: =SUM(J7:J10) -> 78009663 | K12: =SUM(K7:K10) -> -3232201.8
A15: Scenario Output | B15: Value
A16: Selected scenario | B16: =B3 -> Base
A17: Portfolio budget revenue | B17: =F12 -> 147328639
A18: Portfolio scenario revenue | B18: =G12 -> 1.4726326e+08
A19: Portfolio budget EBITDA | B19: =I12 -> 81241865
A20: Portfolio scenario EBITDA | B20: =J12 -> 78009663

Sheet 09_Management_Dashboard
A1: Renewable Energy Portfolio FP&A Dashboard
A2: Monthly performance pack comparing actuals, budget, forecast, and key variance drivers.
A4: Revenue | D4: EBITDA | G4: EBITDA variance | J4: Downtime variance
A5: ='06_Calculations'!B4 -> 136797930 | D5: ='06_Calculations'!B7 -> 62995562 | G5: ='06_Calculations'!E7 -> -18246303 | J5: ='06_Calculations'!E10 -> 947
A58: Management commentary
A59: Actual EBITDA is €18.2M below budget, mainly driven by higher opex, weaker realized prices, and ramp-up delays. Revenue is €10.5M below budget, while forecast revenue remains closer to budget, suggesting partial recovery but continued margin pressure. Noordzee Wind A is the largest downside contributor due to price and downtime exposure. The Hydrogen Pilot remains strategic but loss-making. Management should focus on maintenance control, price exposure, hydrogen ramp-up milestones, and whether battery storage continues to offset part of the portfolio downside.

Sheet 10_Commentary_Pack
A1: Renewable Energy Portfolio Monthly Performance Commentary
A3: Executive summary
A4: Actual EBITDA finished €18.2M below budget, with the downside mainly explained by higher opex, weaker realized prices, and ramp-up delays. Revenue was €10.5M below budget, while forecast revenue remained closer to budget, indicating partial recovery but continued margin pressure.
A7: Key Drivers
A8: 1. Opex was the largest EBITDA drag, reflecting maintenance pressure and higher operating costs.
A9: 2. Price variance was the second largest driver, mainly affecting the wind-heavy portfolio base.
A10: 3. Ramp-up and downtime effects added further downside, especially for the Hydrogen Pilot and Noordzee Wind A.
A12: Asset-level interpretation
A13: Noordzee Wind A remains the largest revenue and EBITDA contributor, but also the largest downside contributor because of price exposure and downtime.
A14: Solar assets performed more steadily, with smaller variance and clearer seasonal patterns.
A15: Rotterdam Battery D showed positive scenario upside, suggesting improving operational contribution.
A16: Groningen Hydrogen Pilot E remains strategically relevant but is currently a short-term EBITDA drag.
... A25: This workbook uses synthetic data created for portfolio demonstration purposes. Figures are illustrative and do not represent any real company, project, or market recommendation.

Sheet 11_PQ_Combined
A1: month | B1: asset_id | C1: production_mwh | D1: realized_price_eur_mwh | E1: revenue_eur | F1: direct_opex_eur | G1: allocated_overhead_eur | H1: ebitda_eur | I1: capex_eur | J1: utilization_pct | K1: downtime_hours | L1: availability_pct | M1: Scenario | N1: asset_name | O1: technology | P1: region | Q1: capacity_mw | R1: asset_status
A2: 45658 | B2: A001 | C2: 62933 | D2: 82.4 | E2: 5185781 | F2: 1247706 | G2: 156000 | H2: 3782075 | I2: 61200 | J2: 0.4699 | K2: 6 | L2: 0.9919 | M2: Actual | N2: Noordzee Wind A | O2: Offshore wind | P2: Netherlands - North Sea | Q2: 180 | R2: Operating
A3: 45689 | B3: A001 | C3: 57178.3 | D3: 79.18 | E3: 4527633 | F3: 1158840 | G3: 156000 | H3: 3212794 | I3: 61200 | J3: 0.4727 | K3: 6 | L3: 0.9911 | M3: Actual | N3: Noordzee Wind A | O3: Offshore wind | P3: Netherlands - North Sea | Q3: 180 | R3: Operating
A4: 45658 | B4: A002 | C4: 3160.7 | D4: 86.15 | E4: 272299 | F4: 106430 | G4: 43050 | H4: 122818 | I4: 8035 | J4: 0.0566 | K4: 2 | L4: 0.9973 | M4: Actual | N4: Flevoland Solar B | O4: Solar PV | P4: Netherlands - Flevoland | Q4: 75 | R4: Operating
A5: 45658 | B5: A003 | C5: 1670.1 | D5: 82.79 | E5: 138261 | F5: 64426 | G5: 30750 | H5: 43085 | I5: 8258 | J5: 0.0534 | K5: 2 | L5: 0.9973 | M5: Actual | N5: Brabant Solar C | O5: Solar PV | P5: Netherlands - Noord-Brabant | Q5: 42 | R5: Operating
A6: 45658 | B6: A004 | C6: 10528.6 | D6: 41.77 | E6: 439751 | F6: 311898 | G6: 67600 | H6: 60252 | I6: 185500 | J6: 0.2359 | K6: 18 | L6: 0.9758 | M6: Actual | N6: Rotterdam Battery D | O6: Battery storage | P6: Netherlands - Zuid-Holland | Q6: 60 | R6: Ramping
A7: 45658 | B7: A005 | C7: 1501 | D7: 117.48 | E7: 176343 | F7: 754744 | G7: 100700 | H7: -679101 | I7: 676000 | J7: 0.1009 | K7: 24 | L7: 0.9677 | M7: Actual | N7: Groningen Hydrogen Pilot E | O7: Hydrogen pilot | P7: Netherlands - Groningen | Q7: 25 | R7: Pilot
A8: 45689 | B8: A002 | C8: 3885.3 | D8: 79.61 | E8: 309293 | F8: 110349 | G8: 43050 | H8: 155894 | I8: 7910 | J8: 0.0771 | K8: 8 | L8: 0.9881 | M8: Actual | N8: Flevoland Solar B | O8: Solar PV | P8: Netherlands - Flevoland | Q8: 75 | R8: Operating
A9: 45689 | B9: A003 | C9: 2333 | D9: 81.31 | E9: 189690 | F9: 66027 | G9: 30750 | H9: 92913 | I9: 8917 | J9: 0.0827 | K9: 8 | L9: 0.9881 | M9: Actual | N9: Brabant Solar C | O9: Solar PV | P9: Netherlands - Noord-Brabant | Q9: 42 | R9: Operating
A10: 45689 | B10: A004 | C10: 10519.2 | D10: 41.5 | E10: 436589 | F10: 358729 | G10: 67600 | H10: 10261 | I10: 185500 | J10: 0.2609 | K10: 14 | L10: 0.9792 | M10: Actual | N10: Rotterdam Battery D | O10: Battery storage | P10: Netherlands - Zuid-Holland | Q10: 60 | R10: Ramping
A11: 45689 | B11: A005 | C11: 1553.9 | D11: 117.96 | E11: 183303 | F11: 753742 | G11: 100700 | H11: -671138 | I11: 676000 | J11: 0.1156 | K11: 24 | L11: 0.9643 | M11: Actual | N11: Groningen Hydrogen Pilot E | O11: Hydrogen pilot | P11: Netherlands - Groningen | Q11: 25 | R11: Pilot
A12: 45717 | B12: A001 | C12: 59753.4 | D12: 77.15 | E12: 4610246 | F12: 1215684 | G12: 156000 | H12: 3238562 | I12: 61200 | J12: 0.4462 | K12: 6 | L12: 0.9919 | M12: Actual | N12: Noordzee Wind A | O12: Offshore wind | P12: Netherlands - North Sea | Q12: 180 | R12: Operating
A13: 45717 | B13: A002 | C13: 6698.1 | D13: 74.04 | E13: 495931 | F13: 120794 | G13: 43050 | H13: 332087 | I13: 28576 | J13: 0.12 | K13: 2 | L13: 0.9973 | M13: Actual | N13: Flevoland Solar B | O13: Solar PV | P13: Netherlands - Flevoland | Q13: 75 | R13: Operating
... A361: 46357 | B361: A005 | C361: 7231.7 | D361: 118 | E361: 853338 | F361: 1088402 | G361: 100700 | H361: -335764 | I361: 462000 | J361: 0.486 | K361: 28 | L361: 0.9624 | M361: Forecast | N361: Groningen Hydrogen Pilot E | O361: Hydrogen pilot | P361: Netherlands - Groningen | Q361: 25 | R361: Pilot

Sheet 12_Input_Assets
A1: asset_id | B1: asset_name | C1: technology | D1: region | E1: capacity_mw | F1: commercial_start_date | G1: ownership_share | H1: asset_status
A2: A001 | B2: Noordzee Wind A | C2: Offshore wind | D2: Netherlands - North Sea | E2: 180 | F2: 44805 | G2: 1 | H2: Operating
A3: A002 | B3: Flevoland Solar B | C3: Solar PV | D3: Netherlands - Flevoland | E3: 75 | F3: 45047 | G3: 1 | H3: Operating
A4: A003 | B4: Brabant Solar C | C4: Solar PV | D4: Netherlands - Noord-Brabant | E4: 42 | F4: 44348 | G4: 1 | H4: Operating
A5: A004 | B5: Rotterdam Battery D | C5: Battery storage | D5: Netherlands - Zuid-Holland | E5: 60 | F5: 45597 | G5: 1 | H5: Ramping
A6: A005 | B6: Groningen Hydrogen Pilot E | C6: Hydrogen pilot | D6: Netherlands - Groningen | E6: 25 | F6: 45717 | G6: 0.8 | H6: Pilot

Sheet 13_Input_Assumptions
A1: scenario | B1: technology | C1: price_index | D1: volume_factor | E1: opex_inflation | F1: downtime_factor | G1: capex_delay_months | H1: commentary
A2: Downside | B2: Offshore wind | C2: 0.918 | D2: 0.921 | E2: 0.099 | F2: 1.5 | G2: 3 | H2: Downside assumption set for offshore wind.
A3: Downside | B3: Solar PV | C3: 0.864 | D3: 0.959 | E3: 0.081 | F3: 0.875 | G3: 3 | H3: Downside assumption set for solar pv.
A4: Downside | B4: Battery storage | C4: 1.008 | D4: 0.996 | E4: 0.095 | F4: 1.312 | G4: 3 | H4: Downside assumption set for battery storage.
A5: Downside | B5: Hydrogen pilot | C5: 0.9 | D5: 0.771 | E5: 0.108 | F5: 1.625 | G5: 5 | H5: Downside assumption set for hydrogen pilot.
A6: Base | B6: Offshore wind | C6: 1.02 | D6: 0.98 | E6: 0.055 | F6: 1.2 | G6: 1 | H6: Base assumption set for offshore wind.
A7: Base | B7: Solar PV | C7: 0.96 | D7: 1.02 | E7: 0.045 | F7: 0.7 | G7: 1 | H7: Base assumption set for solar pv.
A8: Base | B8: Battery storage | C8: 1.12 | D8: 1.06 | E8: 0.053 | F8: 1.05 | G8: 1 | H8: Base assumption set for battery storage.
A9: Base | B9: Hydrogen pilot | C9: 1 | D9: 0.82 | E9: 0.06 | F9: 1.3 | G9: 1 | H9: Base assumption set for hydrogen pilot.
A10: Upside | B10: Offshore wind | C10: 1.102 | D10: 1.019 | E10: 0.039 | F10: 1.02 | G10: 0 | H10: Upside assumption set for offshore wind.
A11: Upside | B11: Solar PV | C11: 1.037 | D11: 1.061 | E11: 0.032 | F11: 0.595 | G11: 0 | H11: Upside assumption set for solar pv.
A12: Upside | B12: Battery storage | C12: 1.21 | D12: 1.102 | E12: 0.037 | F12: 0.892 | G12: 0 | H12: Upside assumption set for battery storage.
A13: Upside | B13: Hydrogen pilot | C13: 1.08 | D13: 0.853 | E13: 0.042 | F13: 1.105 | G13: 0 | H13: Upside assumption set for hydrogen pilot.

Sheet 14_Input_VarianceDrivers
A1: month | B1: asset_id | C1: variance_type | D1: variance_driver | E1: variance_eur | F1: commentary
A2: 45658 | B2: A001 | C2: Price | D2: Noordzee Wind A - Price | E2: -604157 | F2: Actual realized price versus budgeted realized price.
A3: 45658 | B3: A001 | C3: Volume | D3: Noordzee Wind A - Volume | E3: -320804 | F3: Production or throughput variance not separately attributed to downtime or ramp-up.
A4: 45658 | B4: A001 | C4: Downtime | D4: Noordzee Wind A - Downtime | E4: 0 | F4: Estimated EBITDA impact from unplanned downtime above budget.
A5: 45658 | B5: A001 | C5: Ramp-up | D5: Noordzee Wind A - Ramp-up | E5: 0 | F5: Battery/hydrogen ramp-up performance versus plan.
A6: 45658 | B6: A001 | C6: Opex | D6: Noordzee Wind A - Opex | E6: -66346 | F6: Direct operating cost variance; negative values are adverse.
A7: 45658 | B7: A001 | C7: Timing/Mix | D7: Noordzee Wind A - Timing/Mix | E7: -5898 | F7: Residual impact from overhead, capex timing context, rounding, and portfolio mix.
A8: 45658 | B8: A002 | C8: Price | D8: Flevoland Solar B - Price | E8: 3635 | F8: Actual realized price versus budgeted realized price.
A9: 45658 | B9: A002 | C9: Volume | D9: Flevoland Solar B - Volume | E9: 8491 | F9: Production or throughput variance not separately attributed to downtime or ramp-up.
A10: 45658 | B10: A002 | C10: Downtime | D10: Flevoland Solar B - Downtime | E10: 0 | F10: Estimated EBITDA impact from unplanned downtime above budget.
A11: 45658 | B11: A002 | C11: Ramp-up | D11: Flevoland Solar B - Ramp-up | E11: 0 | F11: Battery/hydrogen ramp-up performance versus plan.
A12: 45658 | B12: A002 | C12: Opex | D12: Flevoland Solar B - Opex | E12: -1636 | F12: Direct operating cost variance; negative values are adverse.
A13: 45658 | B13: A002 | C13: Timing/Mix | D13: Flevoland Solar B - Timing/Mix | E13: -1041 | F13: Residual impact from overhead, capex timing context, rounding, and portfolio mix.
... A721: 46357 | B721: A005 | C721: Timing/Mix | D721: Groningen Hydrogen Pilot E - Timing/Mix | E721: -5675 | F721: Residual impact from overhead, capex timing context, rounding, and portfolio mix.
